[
  {
    "id" : 1,
    "name": "AMOUR Tshirt",
    "price": "39.90",
    "image": "/AmourB01.jpg",
    "image2": "/AmourB02.jpg"
  },
  {
    "id" : 2,
    "name": "Elegence Pant",
    "price": "49.90",
    "image": "/ElegenceW01.jpg",
    "image2": "/ElegenceW03.jpg"
  },
  {
    "id" : 3,
    "name": "Arcade Jacket",
    "price": "49.90",
    "image": "/ArcadeC01.jpg",
    "image2": "/ArcadeC04.jpg"
  },
  {
    "id" : 4,
    "name": "Tokyo Tshirt",
    "price": "39.90",
    "image": "/TokyoW01.jpg",
    "image2": "/TokyoW04.jpg"
  },
  {
    "id" : 5,
    "name": "Art Sweat",
    "price": "49.90",
    "image": "/ArtPO01.jpg",
    "image2": "/ArtPO04.jpg"
  },
  {
    "id" : 6,
    "name": "Elite Pant",
    "price": "49.90",
    "image": "/EliteB01.jpg",
    "image2": "/EliteB02.jpg"
  }
]